[
  {
    "gameCode": "PAN",
    "dllName": "nostalgia.dll",
    "lastUpdated": "2025-01-17",
    "source": "https://sp2x.two-torial.xyz/"
  },
  {
    "type": "memory",
    "name": "Menu Timer Freeze",
    "description": "Freezes menu timers.",
    "patches": [
      {
        "start": 3100000,
        "signature": "41 FF C8 33 FF",
        "data": "90 90 90"
      }
    ]
  },
  {
    "type": "memory",
    "name": "Shorter Monitor Check",
    "description": "Similar to Op.2, recommended only if you have a stable framerate.",
    "patches": [
      {
        "start": 2100000,
        "signature": "83 FA 1E 7C ?? 49 63 80",
        "adjust": 2,
        "data": "00"
      }
    ]
  },
  {
    "type": "memory",
    "name": "Unscramble Touch Screen Keypad",
    "description": "Unscrambles the touchscreen's Keypad.",
    "patches": [
      {
        "start": 2800000,
        "signature": "48 8D 0C ?? 48 03 C9 8B 04",
        "data": "48 C7 C1 78 00 00 00"
      }
    ]
  },
  {
    "type": "memory",
    "name": "Hide \"EXTRA PASELI: %d\" Text",
    "description": "Hides the bottom text \"EXTRA PASELI: %d\".",
    "patches": [
      {
        "start": 6000000,
        "signature": "45 58 54 52 41 20 50 41 53 45 4C 49 3A 20 25 73 00 00 00 00 00 00 00 00   ",
        "data": "00 58 54",
        "patchall": "true"
      }
    ]
  },
  {
    "type": "memory",
    "name": "Hide \"PASELI: *****\" Text",
    "description": "Hides the bottom text \"PASELI: *****\".",
    "patches": [
      {
        "start": 3100000,
        "signature": "FF 15 ?? ?? ?? ?? 48 8D 15 ?? ?? ?? ?? B9 0C 00 00 00",
        "data": "E9 AD 01 00 00 90"
      }
    ]
  },
  {
    "type": "memory",
    "name": "Hide Credit/Coin Text",
    "description": "Hides \"CREDIT: %d\" and \"CREDIT %d  COIN: %d / %d\".",
    "patches": [
      {
        "start": 6000000,
        "signature": "43 52 45 44 49 54 3A 20 25 64 00",
        "data": "00 52 45"
      },
      {
        "start": 6000000,
        "signature": "43 52 45 44 49 54 3A 20 25 64 20",
        "data": "00 52 45"
      }
    ]
  }
]
